Metadata-Version: 2.1
Name: wechat-python
Version: 0.5.8
Summary: Wechat for Python
Home-page: https://github.com/wpcfan/weixin-python
Author: zwczou
Author-email: zwczou@gmail.com
License: BSD
Keywords: weixin,weixin pay,weixin login,weixin mp,weixin python,wechat,wechat pay,wechat login,wechat mp,wechat python
Platform: any
